atgui/__init__.py
atgui/core.py
atgui/menus.py
atgui/utils.py
atgui-1.0.2.dist-info/licenses/LICENSE
atgui-1.0.2.dist-info/METADATA
atgui-1.0.2.dist-info/WHEEL
atgui-1.0.2.dist-info/top_level.txt
atgui-1.0.2.dist-info/RECORD
