Metadata-Version: 2.4
Name: atgui
Version: 1.0.2
Summary: ATGUI - Advanced Terminal GUI, Makes making Terminal GUI's easier and better!
Author-email: Raynixx <4raynixx@gmail.com>, ChickenStrips05 <chickenstrips05@proton.me>
License-Expression: AGPL-3.0-or-later
Classifier: Programming Language :: Python :: 3
Classifier: Operating System :: OS Independent
Requires-Python: >=3.9
License-File: LICENSE
Dynamic: license-file
